[
  {
    "@title": "IBM OS/2 1.0",
    "@preview": "/software/pcx86/sys/os2/ibm/1.0/screenshot.png",
    "@permalink": "/software/pcx86/sys/os2/ibm/1.0/",
    "@tags": "home"
  },
  {
    "@title": "VisiCalc (1981)",
    "@preview": "/software/pcx86/app/other/visicalc/1981/screenshot.png",
    "@permalink": "/software/pcx86/app/other/visicalc/1981/",
    "@tags": "home"
  },
  {
    "@title": "DONKEY.BAS from PC DOS 1.00 (1981)",
    "@preview": "/software/pcx86/sys/dos/ibm/1.00/basic/donkey/screenshot.png",
    "@permalink": "/software/pcx86/sys/dos/ibm/1.00/basic/donkey/",
    "@tags": "home"
  }
]
